{
  "url": "https://ecommercegermany.com/blog/october-2023-e-commerce-insights-mid-month-news-review/",
  "title": "October 2023 E-commerce Insights Mid-Month News Review - E-commerce Germany News",
  "snippet": "Queenly, a resale website, has started using generative AI to create virtual fashion items for its platform. This innovative approach allows",
  "domain": "ecommercegermany.com",
  "publishedDate": "2023-10-11T17:11:00+02:00",
  "extractedText": "News business strategyeuroperetail October 2023 E-commerce Insights Mid-Month News Review Written by Kinga Edwards Published on 11.10.2023 Introduction Chapters Share this article Copied LinkedIn Twitter Facebook Reaching the middle of October 2023, the e-commerce landscape continues to shift and adapt, offering a plethora of developments that industry stakeholders should not overlook. From technological innovations to strategic partnerships and market trends, the month has been bustling with news. Our October 2023 E-commerce Insights Mid-Month News Review is here to provide you with a concise yet detailed roundup of these significant happenings. Stay informed and ahead of the curve by diving into this month’s key stories. Homerr and Vinted Join Forces Homerr, a logistics company, has partnered with Vinted, a pre-loved fashion marketplace, to enhance the shipping experience for users. The collaboration aims to make the process of sending and receiving packages more convenient and sustainable. This partnership could set a precedent for how logistics and e-commerce companies can collaborate to improve customer experience and environmental impact. Read more TikTok Halts E-commerce Service in Indonesia TikTok has suspended its e-commerce services in Indonesia following a government ban. The decision comes as a significant setback for the social media giant, which had been making strides in integrating e-commerce features. This development could have broader implications for the role of social media platforms in e-commerce, especially in regulated markets. Read more The Silent Problem Solvers in Fashion A new series by TextilWirtschaft highlights the role of “fashion brokers” who act as intermediaries between brands and retailers. These brokers are becoming increasingly important in navigating the complexities of the fashion industry, especially in the e-commerce space. Their expertise in logistics, brand positioning, and market trends makes them invaluable assets. Read more Prime Day Isn’t Just About Amazon Anymore The concept of “Prime Day” is evolving, with other retailers launching their own versions of the event. This shift indicates that the retail industry is keen to capitalize on the shopping frenzy generated by Amazon’s Prime Day. It’s a strategic move that could lead to more competitive pricing and offers across various online platforms. Read more FedEx’s New Robot for Loading Vans FedEx has introduced a new robot that can load delivery vans efficiently, almost like playing 3D Tetris. This technological advancement could revolutionize the logistics and shipping industry by making the loading process faster and more efficient. It’s an exciting development that showcases how automation is becoming an integral part of e-commerce logistics. Read more Queenly Uses Generative AI for Resale Queenly, a resale website, has started using generative AI to create virtual fashion items for its platform. This innovative approach allows users to visualize how different items would look when paired together, enhancing the online shopping experience. It’s a fascinating use of AI that could set new trends in the e-commerce industry. Read more Mango Shuts Down Marketplace After two years of operation, Mango has decided to shut down its online marketplace. The closure suggests that not all fashion retailers can sustain a marketplace model, raising questions about what it takes to succeed in this competitive space. It’s a cautionary tale for other brands considering a similar venture. Read more Shein’s US Head of Strategy Talks Business Model Shein’s US Head of Strategy has revealed that the company is considering moving beyond its China-centric model. This could mean a significant expansion into other markets and possibly a diversification of its product range. It’s a strategic move that could reshape the fast-fashion e-commerce landscape. Read more Fashionette Launches Platform for Luxury Fashion Fashionette AG has launched a new platform dedicated to luxury fashion. This platform aims to provide a curated experience for consumers looking for high-end fashion items. It’s a strategic move to tap into the growing luxury e-commerce market and could set Fashionette apart from other fashion retailers. Read more Global E-commerce Market Forecast According to GlobalData, the global e-commerce market will be worth $9.3 trillion by 2027. This forecast highlights the immense growth potential of the industry and suggests that businesses should prepare for a highly competitive environment. The report provides valuable insights for stakeholders looking to make informed decisions. Read more Declining Revenue in E-commerce for the First Time For the first time, the EHI Retail Institute has reported a decline in e-commerce revenue. This unexpected trend could be due to various factors, including market saturation or changing consumer behaviors. It’s a development that warrants close attention from industry professionals. Read more Fnac ",
  "wordCount": 977,
  "author": "Kinga Edwards",
  "hash": "1230a54f56e806a2"
}