{
  "url": "https://www.syntacticsinc.com/news-articles-cat/ai-for-ecommerce-tools-strategies-trends/",
  "title": "AI for eCommerce: Tools, Strategies, and Future Trends",
  "snippet": "Redefine your business with AI for eCommerce to boost sales, automate processes, and personalize shopping. Discover the top AI tools, strategies",
  "domain": "syntacticsinc.com",
  "extractedText": "Share Aug 15, 2025 AI for eCommerce: Tools, Strategies, and Future Trends Redefine your business with AI for eCommerce to boost sales, automate processes, and personalize shopping. Discover the top AI tools, strategies, and trends you need. AI (Artificial Intelligence) for eCommerce has transformed the way online businesses operate. From personalized shopping experiences to automated customer service, AI is no longer a futuristic concept. In fact, even global eCommerce giants like Amazon and Alibaba, and small businesses, have been adopting AI to compete on a bigger scale. Source: Shopify This rapid adoption is driven by AI’s ability to simplify processes, reduce operational costs, and enhance customer satisfaction. By analyzing customer behavior, predicting buying trends, and automating repetitive tasks, AI enables businesses to operate more efficiently and competitively. Key Takeaways 95% of eCommerce companies in the U.S. experienced a very good Return on Investment (ROI) when adopting AI technologies. [Statista] Alibaba’s AI-powered recommendations, fueled by vast consumer data, have boosted Click-through Rates (CTRs) by 38% and conversions by 25%. [MindtheProduct] Website visitors from AI search are four times more valuable than organic search visitors. [Semrush] The future of AI in eCommerce includes hyper-personalization, voice commerce, and predictive analytics. Investing in AI now positions your business for long-term success. TABLE OF CONTENTS Key Takeaways 7 Benefits of AI in Online Retail How AI Enhances eCommerce Experiences Top AI Tools for eCommerce Platforms Implementation Best Practices Final Thoughts: Should You Invest Now? FAQs About AI for eCommerce 7 Benefits of AI in Online Retail The growing presence of AI in eCommerce is not just keeping up with technology trends, it’s also about having the business advantage. By combining automated data analytics and advanced algorithms, AI empowers online businesses to meet expectations faster, more innovative, and more effectively. Hyper-Personalized Customer Experiences AI can analyze real-time data to deliver tailored product recommendations, personalized emails, and dynamic landing pages. This includes browsing history, past purchases, and demographic details. In fact, Salesforce reports that 73% of consumers say treating them like an individual rather than a number is key to winning loyalty. This level of personalization increases engagement, average order value (AOV), and customer loyalty. 24/7 Intelligent Customer Support According to CX Today, Gartner predicted that AI-powered support can resolve up to 80% of common customer queries without human intervention. AI chatbots and virtual assistants handle common inquiries, such as order tracking, return policies, and product details, around the clock. This reduces response time from hours to seconds and frees up human agents for complex issues. Smarter Inventory and Supply Chain Management A Study showed that online retailers that use AI for inventory forecasting saw an average 52% improvement in accuracy, leading to a 45% reduction in excess inventory. Using predictive analytics, AI forecasts demand patterns based on seasonality, trends, and external factors (like weather or local events). This helps retailers optimize stock levels, prevent overstocking or stockouts, and improve fulfillment efficiency. Dynamic Pricing Optimization AI algorithms monitor competitor pricing, demand fluctuations, and user behavior to adjust prices in real time. This ensures competitiveness while maximizing profit margins, especially useful during flash sales or holiday seasons. For example, Amazon changes prices every 10 minutes on average, reported a significant increase in gross margins compared to static pricing models. Fraud Detection and Transaction Security Machine learning models detect unusual patterns in transactions, such as multiple failed attempts, mismatched billing addresses, or high-risk geolocations. This helps prevent chargebacks and protects both merchants and customers. This is what happened to JP Morgan, which uses AI-powered fraud shields to reduce scams by 40%. Enhanced Product Search and Discovery Traditional keyword searches are being replaced by AI-driven systems that understand natural language and visual cues. Features like visual search (upload a photo to find products) and semantic search (understanding intent behind queries) dramatically improve user experience. With AI-powered search, it can reduce bounce rates by up to 40% and increase average session duration. Automated Marketing and Campaign Optimization AI also optimizes marketing efforts by predicting which messages resonate best with specific customer segments. From email subject lines to ad targeting, tools like AI copywriters can generate product descriptions and promotional content in seconds. Businesses using AI for marketing report 3x faster campaign deployment and 40% higher ROI (Return on Investment) on ad spend. How AI ",
  "wordCount": 2180,
  "author": "Adam Tan",
  "hash": "7c717ebe53b72ece"
}